binance_sdk_pay/__init__.py
binance_sdk_pay/metadata.py
binance_sdk_pay/pay.py
binance_sdk_pay/rest_api/__init__.py
binance_sdk_pay/rest_api/api/__init__.py
binance_sdk_pay/rest_api/api/pay_api.py
binance_sdk_pay/rest_api/models/__init__.py
binance_sdk_pay/rest_api/models/enums.py
binance_sdk_pay/rest_api/models/get_pay_trade_history_response.py
binance_sdk_pay/rest_api/models/get_pay_trade_history_response_data_inner.py
binance_sdk_pay/rest_api/models/get_pay_trade_history_response_data_inner_funds_detail_inner.py
binance_sdk_pay/rest_api/models/get_pay_trade_history_response_data_inner_funds_detail_inner_wallet_asset_cost_inner.py
binance_sdk_pay/rest_api/models/get_pay_trade_history_response_data_inner_payer_info.py
binance_sdk_pay/rest_api/models/get_pay_trade_history_response_data_inner_receiver_info.py
binance_sdk_pay/rest_api/models/get_pay_trade_history_response_data_inner_receiver_info_extend.py
binance_sdk_pay/rest_api/rest_api.py
binance_sdk_pay-3.2.0.dist-info/METADATA
binance_sdk_pay-3.2.0.dist-info/WHEEL
binance_sdk_pay-3.2.0.dist-info/licenses/LICENCE
binance_sdk_pay-3.2.0.dist-info/RECORD
